datasourcelib/__init__.py
datasourcelib/database.py
datasourcelib/datasource.py
datasourcelib/mongodb.py
datasourcelib/postgresdb.py
datasourcelib/sqlitedb.py
dekeyrej_datasource-0.9.7.dist-info/licenses/LICENSE
dekeyrej_datasource-0.9.7.dist-info/METADATA
dekeyrej_datasource-0.9.7.dist-info/WHEEL
dekeyrej_datasource-0.9.7.dist-info/top_level.txt
dekeyrej_datasource-0.9.7.dist-info/RECORD
