Metadata-Version: 2.4
Name: dekeyrej-datasource
Version: 0.9.7
Summary: Multi-database abstraction layer
Author: J.DeKeyrel
Author-email: "J. DeKeyrel" <noneyabusiness@notemail.com>
License: MIT License
Classifier: License :: OSI Approved :: MIT License
Classifier: Programming Language :: Python
Classifier: Programming Language :: Python :: 3
Requires-Python: >=3.9
License-File: LICENSE
Requires-Dist: arrow
Requires-Dist: pymongo
Requires-Dist: psycopg2-binary>=2.9.5
Dynamic: author
Dynamic: license-file
